docker_ready/__init__.py
docker_ready/get.py
docker_ready/project.py
docker_ready/projects/gitea/compose.yaml
docker_ready/projects/gitea/project.yaml
docker_ready/projects/postgres/compose.yaml
docker_ready/projects/postgres/project.yaml
docker_ready/remove.py
docker_ready/run.py
docker_ready/utils/__init__.py
docker_ready/utils/constants.py
docker_ready/utils/tools.py
docker_ready-0.2.0.dist-info/METADATA
docker_ready-0.2.0.dist-info/WHEEL
docker_ready-0.2.0.dist-info/RECORD
